Metadata-Version: 2.1
Name: odoo-addon-web-drop-target
Version: 15.0.1.0.2
Summary: Allows to drag files into Odoo
Home-page: https://github.com/OCA/web
Author: Therp BV,Odoo Community Association (OCA)
Author-email: support@odoo-community.org
License: LGPL-3
Platform: UNKNOWN
Classifier: Programming Language :: Python
Classifier: Framework :: Odoo
Classifier: Framework :: Odoo :: 15.0
Classifier: License :: OSI Approved :: GNU Lesser General Public License v3 (LGPLv3)
Requires-Python: >=3.8
Requires-Dist: odoo <15.1dev,>=15.0a
